LICENSE
psycopg2/__init__.py
psycopg2/errorcodes.py
psycopg2/extensions.py
psycopg2/extras.py
puff/__init__.py
puff/asyncio_support.py
puff/contrib/.DS_Store
puff/contrib/__init__.py
puff/contrib/django/.DS_Store
puff/contrib/django/__init__.py
puff/contrib/django/management.py
puff/contrib/django/postgres/.DS_Store
puff/contrib/django/postgres/__init__.py
puff/contrib/django/postgres/base.py
puff/contrib/django/postgres/client.py
puff/contrib/django/postgres/creation.py
puff/contrib/django/postgres/features.py
puff/contrib/django/postgres/introspection.py
puff/contrib/django/postgres/operations.py
puff/contrib/django/postgres/schema.py
puff/contrib/django/redis.py
puff/contrib/django/static.py
puff/graphql.py
puff/http.py
puff/json.py
puff/json_impl.py
puff/poetry_plugins.py
puff/postgres.py
puff/pubsub.py
puff/redis.py
puff/task_queue.py
puff_py-0.1.9.dist-info/LICENSE
puff_py-0.1.9.dist-info/WHEEL
puff_py-0.1.9.dist-info/METADATA
puff_py-0.1.9.dist-info/RECORD
