Metadata-Version: 2.1
Name: puff-py
Version: 0.1.9
Summary: Python support for Puff
Home-page: https://github.com/hansonkd/puff
License: MIT
Author: Kyle Hanson
Author-email: me@khanson.io
Requires-Python: >=3.10,<4.0
Classifier: License :: OSI Approved :: MIT License
Classifier: Programming Language :: Python :: 3
Classifier: Programming Language :: Python :: 3.10
Classifier: Programming Language :: Python :: 3.11
Requires-Dist: asgiref (>=3.5.2,<4.0.0)
Requires-Dist: greenlet (>=2.0.1,<3.0.0)
Project-URL: Repository, https://github.com/hansonkd/puff-rs
